trycicle/__init__.py
trycicle/__main__.py
trycicle/arguments.py
trycicle/cache.py
trycicle/cli.py
trycicle/git_clone.py
trycicle/glob.py
trycicle/include.py
trycicle/interpolation.py
trycicle/models.py
trycicle/parser.py
trycicle/run.py
trycicle/subprocess.py
trycicle/variables.py
trycicle-0.6.0.dist-info/entry_points.txt
trycicle-0.6.0.dist-info/LICENSE
trycicle-0.6.0.dist-info/WHEEL
trycicle-0.6.0.dist-info/METADATA
trycicle-0.6.0.dist-info/RECORD
