Metadata-Version: 2.1
Name: trycicle
Version: 0.6.0
Summary: Try CI jobs locally
Author-email: Paul Hooijenga <paul@founda.com>
Requires-Python: ~= 3.11
Classifier: Programming Language :: Python :: 3
Classifier: Operating System :: POSIX
Classifier: License :: OSI Approved :: MIT License
Requires-Dist: pyyaml ~= 6.0
Requires-Dist: docker ~= 7.0
Requires-Dist: click ~= 8.1
Requires-Dist: platformdirs ~= 4.2
Requires-Dist: requests ~= 2.32
Project-URL: Homepage, https://gitlab.com/phooijenga/trycicle
